{"_invocation_id": "11f82815-27f9-4cf1-9ce5-edb437f337e0", "linked": {"0": {"name": "model.weather_data.hub_office", "type": "model", "succ": [7, 8, 9, 10, 24, 55]}, "1": {"name": "model.weather_data.bronze_points", "type": "model", "succ": [0, 2, 13, 14, 34, 35, 72]}, "2": {"name": "model.weather_data.hub_resort", "type": "model", "succ": [3, 4, 5, 6, 20, 22, 26, 28, 47, 63]}, "3": {"name": "test.weather_data.not_null_hub_resort_resort_key.f7603134a0", "type": "test"}, "4": {"name": "test.weather_data.unique_hub_resort_resort_key.6803b1f5cb", "type": "test"}, "5": {"name": "test.weather_data.not_null_hub_resort_resort_name.8fdc362a08", "type": "test"}, "6": {"name": "test.weather_data.unique_hub_resort_resort_name.0442b3af7a", "type": "test"}, "7": {"name": "test.weather_data.not_null_hub_office_office_key.e2f7485b65", "type": "test"}, "8": {"name": "test.weather_data.unique_hub_office_office_key.520c5ad6dc", "type": "test"}, "9": {"name": "test.weather_data.not_null_hub_office_office_id.f427cc1370", "type": "test"}, "10": {"name": "test.weather_data.unique_hub_office_office_id.db3483d429", "type": "test"}, "11": {"name": "model.weather_data.sat_grid_data", "type": "model", "succ": [19, 20]}, "12": {"name": "model.weather_data.bronze_grid_data", "type": "model", "succ": [11]}, "13": {"name": "model.weather_data.sat_resort_details", "type": "model", "succ": [21, 22]}, "14": {"name": "model.weather_data.sat_office_details", "type": "model", "succ": [23, 24]}, "15": {"name": "model.weather_data.sat_forecast_period", "type": "model", "succ": [25, 26]}, "16": {"name": "model.weather_data.bronze_forecast_periods", "type": "model", "succ": [15, 75, 76]}, "17": {"name": "model.weather_data.sat_forecast_hourly", "type": "model", "succ": [27, 28]}, "18": {"name": "model.weather_data.bronze_hourly_periods", "type": "model", "succ": [17, 77, 78]}, "19": {"name": "test.weather_data.not_null_sat_grid_data_resort_key.fdab878473", "type": "test"}, "20": {"name": "test.weather_data.relationships_sat_grid_data_resort_key__resort_key__ref_hub_resort_.1bced2954a", "type": "test"}, "21": {"name": "test.weather_data.not_null_sat_resort_details_resort_key.4e9f6ccf4e", "type": "test"}, "22": {"name": "test.weather_data.relationships_sat_resort_details_resort_key__resort_key__ref_hub_resort_.68acfece8d", "type": "test"}, "23": {"name": "test.weather_data.not_null_sat_office_details_office_key.bd47190e47", "type": "test"}, "24": {"name": "test.weather_data.relationships_sat_office_details_office_key__office_key__ref_hub_office_.1a592f0f78", "type": "test"}, "25": {"name": "test.weather_data.not_null_sat_forecast_period_resort_key.2befd63455", "type": "test"}, "26": {"name": "test.weather_data.relationships_sat_forecast_period_resort_key__resort_key__ref_hub_resort_.956e7a6f8b", "type": "test"}, "27": {"name": "test.weather_data.not_null_sat_forecast_hourly_resort_key.982b3ce5e9", "type": "test"}, "28": {"name": "test.weather_data.relationships_sat_forecast_hourly_resort_key__resort_key__ref_hub_resort_.ce9791f375", "type": "test"}, "29": {"name": "model.weather_data.sat_station_details", "type": "model", "succ": [40, 41]}, "30": {"name": "model.weather_data.bronze_stations", "type": "model", "succ": [29, 36]}, "31": {"name": "model.weather_data.sat_zone_details", "type": "model", "succ": [42, 43]}, "32": {"name": "model.weather_data.bronze_zones", "type": "model", "succ": [31, 33]}, "33": {"name": "model.weather_data.hub_zone", "type": "model", "succ": [43, 49, 53, 56, 57, 58, 59]}, "34": {"name": "model.weather_data.link_resort_zone", "type": "model", "succ": [44, 45, 46, 47, 48, 49]}, "35": {"name": "model.weather_data.link_zone_office", "type": "model", "succ": [50, 51, 52, 53, 54, 55]}, "36": {"name": "model.weather_data.hub_station", "type": "model", "succ": [41, 65, 67, 68, 69, 70, 71]}, "37": {"name": "model.weather_data.link_resort_station", "type": "model", "succ": [60, 61, 62, 63, 64, 65]}, "38": {"name": "model.weather_data.bronze_observations", "type": "model", "succ": [37, 39, 73, 74]}, "39": {"name": "model.weather_data.sat_observation", "type": "model", "succ": [66, 67]}, "40": {"name": "test.weather_data.not_null_sat_station_details_station_key.7ea80fa0ce", "type": "test"}, "41": {"name": "test.weather_data.relationships_sat_station_details_station_key__station_key__ref_hub_station_.f4f240b47d", "type": "test"}, "42": {"name": "test.weather_data.not_null_sat_zone_details_zone_key.60bb42abfe", "type": "test"}, "43": {"name": "test.weather_data.relationships_sat_zone_details_zone_key__zone_key__ref_hub_zone_.48a689019a", "type": "test"}, "44": {"name": "test.weather_data.not_null_link_resort_zone_link_key.e7cb224eb0", "type": "test"}, "45": {"name": "test.weather_data.unique_link_resort_zone_link_key.1d3bc6f118", "type": "test"}, "46": {"name": "test.weather_data.not_null_link_resort_zone_resort_key.9ed2ceb51a", "type": "test"}, "47": {"name": "test.weather_data.relationships_link_resort_zone_resort_key__resort_key__ref_hub_resort_.affc971e70", "type": "test"}, "48": {"name": "test.weather_data.not_null_link_resort_zone_zone_key.98a42dd413", "type": "test"}, "49": {"name": "test.weather_data.relationships_link_resort_zone_zone_key__zone_key__ref_hub_zone_.79216dadb8", "type": "test"}, "50": {"name": "test.weather_data.not_null_link_zone_office_link_key.99a2059301", "type": "test"}, "51": {"name": "test.weather_data.unique_link_zone_office_link_key.d3eabfbc86", "type": "test"}, "52": {"name": "test.weather_data.not_null_link_zone_office_zone_key.745502596b", "type": "test"}, "53": {"name": "test.weather_data.relationships_link_zone_office_zone_key__zone_key__ref_hub_zone_.7b4d73f29d", "type": "test"}, "54": {"name": "test.weather_data.not_null_link_zone_office_office_key.533f984fad", "type": "test"}, "55": {"name": "test.weather_data.relationships_link_zone_office_office_key__office_key__ref_hub_office_.4bce9b0ea6", "type": "test"}, "56": {"name": "test.weather_data.not_null_hub_zone_zone_key.ea166a9b96", "type": "test"}, "57": {"name": "test.weather_data.unique_hub_zone_zone_key.342dae8e5d", "type": "test"}, "58": {"name": "test.weather_data.not_null_hub_zone_zone_id.01e9dd68b4", "type": "test"}, "59": {"name": "test.weather_data.unique_hub_zone_zone_id.f52a1a5e06", "type": "test"}, "60": {"name": "test.weather_data.not_null_link_resort_station_link_key.f79a0fef0c", "type": "test"}, "61": {"name": "test.weather_data.unique_link_resort_station_link_key.2ae2a19156", "type": "test"}, "62": {"name": "test.weather_data.not_null_link_resort_station_resort_key.3954a925cd", "type": "test"}, "63": {"name": "test.weather_data.relationships_link_resort_station_resort_key__resort_key__ref_hub_resort_.f991053bf7", "type": "test"}, "64": {"name": "test.weather_data.not_null_link_resort_station_station_key.74f7aee587", "type": "test"}, "65": {"name": "test.weather_data.relationships_link_resort_station_station_key__station_key__ref_hub_station_.75c096feb3", "type": "test"}, "66": {"name": "test.weather_data.not_null_sat_observation_station_key.cbd466fb15", "type": "test"}, "67": {"name": "test.weather_data.relationships_sat_observation_station_key__station_key__ref_hub_station_.8c5ec21e08", "type": "test"}, "68": {"name": "test.weather_data.not_null_hub_station_station_key.48efdcfe11", "type": "test"}, "69": {"name": "test.weather_data.unique_hub_station_station_key.000ee550a6", "type": "test"}, "70": {"name": "test.weather_data.not_null_hub_station_station_id.4599713979", "type": "test"}, "71": {"name": "test.weather_data.unique_hub_station_station_id.ca1249b519", "type": "test"}, "72": {"name": "test.weather_data.not_null_bronze_points_identifier.8017920688", "type": "test"}, "73": {"name": "test.weather_data.not_null_bronze_observations_station_id.b3b77ba6bd", "type": "test"}, "74": {"name": "test.weather_data.not_null_bronze_observations_observation_time.700c15cbc5", "type": "test"}, "75": {"name": "test.weather_data.not_null_bronze_forecast_periods_identifier.3484a4e9de", "type": "test"}, "76": {"name": "test.weather_data.not_null_bronze_forecast_periods_period_number.f4113abcb9", "type": "test"}, "77": {"name": "test.weather_data.not_null_bronze_hourly_periods_identifier.477a3dae8a", "type": "test"}, "78": {"name": "test.weather_data.not_null_bronze_hourly_periods_start_time.16ed2b5efc", "type": "test"}}}